README.txt
setup.cfg
setup.py
docs/HISTORY.txt
rbco/__init__.py
rbco.statcvswrapper.egg-info/PKG-INFO
rbco.statcvswrapper.egg-info/SOURCES.txt
rbco.statcvswrapper.egg-info/dependency_links.txt
rbco.statcvswrapper.egg-info/entry_points.txt
rbco.statcvswrapper.egg-info/namespace_packages.txt
rbco.statcvswrapper.egg-info/not-zip-safe
rbco.statcvswrapper.egg-info/requires.txt
rbco.statcvswrapper.egg-info/top_level.txt
rbco/statcvswrapper/__init__.py
rbco/statcvswrapper/format.py
rbco/statcvswrapper/main.py