Metadata-Version: 1.0
Name: rbco.statcvswrapper
Version: 0.2
Summary: Very simple package to make use of StatCVS easier.
Home-page: UNKNOWN
Author: Rafael Oliveira
Author-email: rafaelbco@gmail.com
License: GPL
Keywords: cvs
Platform: UNKNOWN
Classifier: Programming Language :: Python
